MANIFEST.in
README.md
requirements.txt
setup.py
cxyx/__init__.py
cxyx/__main__.py
cxyx.egg-info/PKG-INFO
cxyx.egg-info/SOURCES.txt
cxyx.egg-info/dependency_links.txt
cxyx.egg-info/entry_points.txt
cxyx.egg-info/not-zip-safe
cxyx.egg-info/requires.txt
cxyx.egg-info/top_level.txt
cxyx/backend/__init__.py
cxyx/backend/backend_result.py
cxyx/broker/__init__.py
cxyx/core/__init__.py
cxyx/core/add_feature.py
cxyx/core/base.py
cxyx/core/config.py
cxyx/core/cxyx.py
cxyx/utils/__init__.py
cxyx/utils/logger.py
cxyx/utils/redis_engine.py